Workbook
Name ScenarioList: Assumed_scenario!$A$2:$A$6

Sheet 1_Actuals_Overview
A1: Vantage Tech Supplies Ltd — Actuals Overview (2023-2025)
A2: UK Region | How we got here: revenue, margin, and where the erosion is coming from
A4: Net revenue growth (23-25) | C4: Gross margin % change | E4: 2025 Net Revenue | G4: 2025 Gross Margin %
A5: =Actuals_Summary!D7/Actuals_Summary!D5-1 -> 0.40690034 | C5: =Actuals_Summary!G7-Actuals_Summary!G5 -> -0.031311927 | E5: =Actuals_Summary!D7 -> 12796433 | G5: =Actuals_Summary!G7 -> 0.22986677
A8: Net revenue, gross margin & GM% — 2023-2025 actual
A9: Year | B9: Net_Revenue | C9: Gross_Margin | D9: Gross_Margin_%
A10: 2023 | B10: =INDEX(Actuals_Summary!$D$5:$D$7,MATCH($A10,Actuals_Summary!$A$5:$A$7,0)) -> 9095479.6 | C10: =INDEX(Actuals_Summary!$F$5:$F$7,MATCH($A10,Actuals_Summary!$A$5:$A$7,0)) -> 2375545.5 | D10: =INDEX(Actuals_Summary!$G$5:$G$7,MATCH($A10,Actuals_Summary!$A$5:$A$7,0)) -> 0.26117869
A11: 2024 | B11: =INDEX(Actuals_Summary!$D$5:$D$7,MATCH($A11,Actuals_Summary!$A$5:$A$7,0)) -> 10782900 | C11: =INDEX(Actuals_Summary!$F$5:$F$7,MATCH($A11,Actuals_Summary!$A$5:$A$7,0)) -> 2665259.9 | D11: =INDEX(Actuals_Summary!$G$5:$G$7,MATCH($A11,Actuals_Summary!$A$5:$A$7,0)) -> 0.24717468
A12: 2025 | B12: =INDEX(Actuals_Summary!$D$5:$D$7,MATCH($A12,Actuals_Summary!$A$5:$A$7,0)) -> 12796433 | C12: =INDEX(Actuals_Summary!$F$5:$F$7,MATCH($A12,Actuals_Summary!$A$5:$A$7,0)) -> 2941474.7 | D12: =INDEX(Actuals_Summary!$G$5:$G$7,MATCH($A12,Actuals_Summary!$A$5:$A$7,0)) -> 0.22986677
A14: Key diagnostic findings
A15: • Not discounting — weighted avg. discount flat at ~10% company-wide, all 3 years.
A16: • Not mix shift — revenue share by category/channel/segment/region barely moved.
A17: • Unit cost inflation (+12.1%) is outrunning price growth (+7.6%) on every SKU.
A18: • Laptops = 62% of revenue and the fastest-eroding margin category.
A19: • Distributor channel: largest (31% of revenue) and structurally lowest-margin.

Sheet Actuals_Summary
A1: Vantage Tech Supplies Ltd — Actuals Summary (2023-2025)
A3: Company-wide yearly totals
A4: Year | B4: Units_Sold | C4: Gross_Revenue | D4: Net_Revenue | E4: Total_Cost | F4: Gross_Margin | G4: Gross_Margin_%
A5: 2023 | B5: =SUMIFS(Sales_Data!$H$2:$H$865,Sales_Data!$B$2:$B$865,$A5) -> 77492 | C5: =SUMIFS(Sales_Data!$K$2:$K$865,Sales_Data!$B$2:$B$865,$A5) -> 10064191 | D5: =SUMIFS(Sales_Data!$L$2:$L$865,Sales_Data!$B$2:$B$865,$A5) -> 9095479.6 | E5: =SUMIFS(Sales_Data!$N$2:$N$865,Sales_Data!$B$2:$B$865,$A5) -> 6719934.1 | F5: =D5-E5 -> 2375545.5 | G5: =IF(D5=0,0,F5/D5) -> 0.26117869
A6: 2024 | B6: =SUMIFS(Sales_Data!$H$2:$H$865,Sales_Data!$B$2:$B$865,$A6) -> 88580 | C6: =SUMIFS(Sales_Data!$K$2:$K$865,Sales_Data!$B$2:$B$865,$A6) -> 11932180 | D6: =SUMIFS(Sales_Data!$L$2:$L$865,Sales_Data!$B$2:$B$865,$A6) -> 10782900 | E6: =SUMIFS(Sales_Data!$N$2:$N$865,Sales_Data!$B$2:$B$865,$A6) -> 8117640.3 | F6: =D6-E6 -> 2665259.9 | G6: =IF(D6=0,0,F6/D6) -> 0.24717468
A7: 2025 | B7: =SUMIFS(Sales_Data!$H$2:$H$865,Sales_Data!$B$2:$B$865,$A7) -> 101349 | C7: =SUMIFS(Sales_Data!$K$2:$K$865,Sales_Data!$B$2:$B$865,$A7) -> 14162888 | D7: =SUMIFS(Sales_Data!$L$2:$L$865,Sales_Data!$B$2:$B$865,$A7) -> 12796433 | E7: =SUMIFS(Sales_Data!$N$2:$N$865,Sales_Data!$B$2:$B$865,$A7) -> 9854958.5 | F7: =D7-E7 -> 2941474.7 | G7: =IF(D7=0,0,F7/D7) -> 0.22986677
A10: Yearly breakdown by SKU
A11: Year | B11: SKU_ID | C11: Product_Name | D11: Lifecycle_Stage | E11: Units_Sold | F11: Gross_Revenue | G11: Net_Revenue | H11: Total_Cost | I11: Gross_Margin | J11: Gross_Margin_%
A12: 2023 | B12: LAP-AIR-13 | C12: =INDEX(Master_Data!$B$2:$B$7,MATCH($B12,Master_Data!$A$2:$A$7,0)) -> AeroBook 13 Laptop | D12: =INDEX(Master_Data!$F$2:$F$7,MATCH($B12,Master_Data!$A$2:$A$7,0)) -> Growth | E12: =SUMIFS(Sales_Data!$H$2:$H$865,Sales_Data!$B$2:$B$865,$A12,Sales_Data!$G$2:$G$865,$B12) -> 6320 | F12: =SUMIFS(Sales_Data!$K$2:$K$865,Sales_Data!$B$2:$B$865,$A12,Sales_Data!$G$2:$G$865,$B12) -> 3120397.1 | G12: =SUMIFS(Sales_Data!$L$2:$L$865,Sales_Data!$B$2:$B$865,$A12,Sales_Data!$G$2:$G$865,$B12) -> 2819760 | H12: =SUMIFS(Sales_Data!$N$2:$N$865,Sales_Data!$B$2:$B$865,$A12,Sales_Data!$G$2:$G$865,$B12) -> 2336346.1 | I12: =G12-H12 -> 483413.94 | J12: =IF(G12=0,0,I12/G12) -> 0.17143797
A13: 2023 | B13: LAP-PRO-15 | C13: =INDEX(Master_Data!$B$2:$B$7,MATCH($B13,Master_Data!$A$2:$A$7,0)) -> ProBook 15 Laptop | D13: =INDEX(Master_Data!$F$2:$F$7,MATCH($B13,Master_Data!$A$2:$A$7,0)) -> Mature | E13: =SUMIFS(Sales_Data!$H$2:$H$865,Sales_Data!$B$2:$B$865,$A13,Sales_Data!$G$2:$G$865,$B13) -> 4542 | F13: =SUMIFS(Sales_Data!$K$2:$K$865,Sales_Data!$B$2:$B$865,$A13,Sales_Data!$G$2:$G$865,$B13) -> 3182543.3 | G13: =SUMIFS(Sales_Data!$L$2:$L$865,Sales_Data!$B$2:$B$865,$A13,Sales_Data!$G$2:$G$865,$B13) -> 2878281.5 | H13: =SUMIFS(Sales_Data!$N$2:$N$865,Sales_Data!$B$2:$B$865,$A13,Sales_Data!$G$2:$G$865,$B13) -> 2491514.1 | I13: =G13-H13 -> 386767.42 | J13: =IF(G13=0,0,I13/G13) -> 0.13437442
A14: 2023 | B14: TAB-LITE-10 | C14: =INDEX(Master_Data!$B$2:$B$7,MATCH($B14,Master_Data!$A$2:$A$7,0)) -> LiteTab 10 Tablet | D14: =INDEX(Master_Data!$F$2:$F$7,MATCH($B14,Master_Data!$A$2:$A$7,0)) -> Growth | E14: =SUMIFS(Sales_Data!$H$2:$H$865,Sales_Data!$B$2:$B$865,$A14,Sales_Data!$G$2:$G$865,$B14) -> 9713 | F14: =SUMIFS(Sales_Data!$K$2:$K$865,Sales_Data!$B$2:$B$865,$A14,Sales_Data!$G$2:$G$865,$B14) -> 2165892.5 | G14: =SUMIFS(Sales_Data!$L$2:$L$865,Sales_Data!$B$2:$B$865,$A14,Sales_Data!$G$2:$G$865,$B14) -> 1939230.1 | H14: =SUMIFS(Sales_Data!$N$2:$N$865,Sales_Data!$B$2:$B$865,$A14,Sales_Data!$G$2:$G$865,$B14) -> 1467148.6 | I14: =G14-H14 -> 472081.46 | J14: =IF(G14=0,0,I14/G14) -> 0.24343757
A15: 2023 | B15: ACC-MSE-WL | C15: =INDEX(Master_Data!$B$2:$B$7,MATCH($B15,Master_Data!$A$2:$A$7,0)) -> Wireless Mouse | D15: =INDEX(Master_Data!$F$2:$F$7,MATCH($B15,Master_Data!$A$2:$A$7,0)) -> Mature | E15: =SUMIFS(Sales_Data!$H$2:$H$865,Sales_Data!$B$2:$B$865,$A15,Sales_Data!$G$2:$G$865,$B15) -> 37496 | F15: =SUMIFS(Sales_Data!$K$2:$K$865,Sales_Data!$B$2:$B$865,$A15,Sales_Data!$G$2:$G$865,$B15) -> 417970.68 | G15: =SUMIFS(Sales_Data!$L$2:$L$865,Sales_Data!$B$2:$B$865,$A15,Sales_Data!$G$2:$G$865,$B15) -> 374488.75 | H15: =SUMIFS(Sales_Data!$N$2:$N$865,Sales_Data!$B$2:$B$865,$A15,Sales_Data!$G$2:$G$865,$B15) -> 208665.33 | I15: =G15-H15 -> 165823.42 | J15: =IF(G15=0,0,I15/G15) -> 0.44279947
A16: 2023 | B16: SW-OFF-365 | C16: =INDEX(Master_Data!$B$2:$B$7,MATCH($B16,Master_Data!$A$2:$A$7,0)) -> Office Software Bundle | D16: =INDEX(Master_Data!$F$2:$F$7,MATCH($B16,Master_Data!$A$2:$A$7,0)) -> Growth | E16: =SUMIFS(Sales_Data!$H$2:$H$865,Sales_Data!$B$2:$B$865,$A16,Sales_Data!$G$2:$G$865,$B16) -> 10804 | F16: =SUMIFS(Sales_Data!$K$2:$K$865,Sales_Data!$B$2:$B$865,$A16,Sales_Data!$G$2:$G$865,$B16) -> 731380 | G16: =SUMIFS(Sales_Data!$L$2:$L$865,Sales_Data!$B$2:$B$865,$A16,Sales_Data!$G$2:$G$865,$B16) -> 665999.02 | H16: =SUMIFS(Sales_Data!$N$2:$N$865,Sales_Data!$B$2:$B$865,$A16,Sales_Data!$G$2:$G$865,$B16) -> 154605.24 | I16: =G16-H16 -> 511393.78 | J16: =IF(G16=0,0,I16/G16) -> 0.76785966
A17: 2023 | B17: WAR-EXT-2Y | C17: =INDEX(Master_Data!$B$2:$B$7,MATCH($B17,Master_Data!$A$2:$A$7,0)) -> Extended Warranty 2Y | D17: =INDEX(Master_Data!$F$2:$F$7,MATCH($B17,Master_Data!$A$2:$A$7,0)) -> Mature | E17: =SUMIFS(Sales_Data!$H$2:$H$865,Sales_Data!$B$2:$B$865,$A17,Sales_Data!$G$2:$G$865,$B17) -> 8617 | F17: =SUMIFS(Sales_Data!$K$2:$K$865,Sales_Data!$B$2:$B$865,$A17,Sales_Data!$G$2:$G$865,$B17) -> 446007.22 | G17: =SUMIFS(Sales_Data!$L$2:$L$865,Sales_Data!$B$2:$B$865,$A17,Sales_Data!$G$2:$G$865,$B17) -> 417720.18 | H17: =SUMIFS(Sales_Data!$N$2:$N$865,Sales_Data!$B$2:$B$865,$A17,Sales_Data!$G$2:$G$865,$B17) -> 61654.73 | I17: =G17-H17 -> 356065.45 | J17: =IF(G17=0,0,I17/G17) -> 0.85240184
A18: 2024 | B18: LAP-AIR-13 | C18: =INDEX(Master_Data!$B$2:$B$7,MATCH($B18,Master_Data!$A$2:$A$7,0)) -> AeroBook 13 Laptop | D18: =INDEX(Master_Data!$F$2:$F$7,MATCH($B18,Master_Data!$A$2:$A$7,0)) -> Growth | E18: =SUMIFS(Sales_Data!$H$2:$H$865,Sales_Data!$B$2:$B$865,$A18,Sales_Data!$G$2:$G$865,$B18) -> 7528 | F18: =SUMIFS(Sales_Data!$K$2:$K$865,Sales_Data!$B$2:$B$865,$A18,Sales_Data!$G$2:$G$865,$B18) -> 3810063.7 | G18: =SUMIFS(Sales_Data!$L$2:$L$865,Sales_Data!$B$2:$B$865,$A18,Sales_Data!$G$2:$G$865,$B18) -> 3442056.8 | H18: =SUMIFS(Sales_Data!$N$2:$N$865,Sales_Data!$B$2:$B$865,$A18,Sales_Data!$G$2:$G$865,$B18) -> 2908114.6 | I18: =G18-H18 -> 533942.2 | J18: =IF(G18=0,0,I18/G18) -> 0.15512301
A19: 2024 | B19: LAP-PRO-15 | C19: =INDEX(Master_Data!$B$2:$B$7,MATCH($B19,Master_Data!$A$2:$A$7,0)) -> ProBook 15 Laptop | D19: =INDEX(Master_Data!$F$2:$F$7,MATCH($B19,Master_Data!$A$2:$A$7,0)) -> Mature | E19: =SUMIFS(Sales_Data!$H$2:$H$865,Sales_Data!$B$2:$B$865,$A19,Sales_Data!$G$2:$G$865,$B19) -> 5072 | F19: =SUMIFS(Sales_Data!$K$2:$K$865,Sales_Data!$B$2:$B$865,$A19,Sales_Data!$G$2:$G$865,$B19) -> 3642530.3 | G19: =SUMIFS(Sales_Data!$L$2:$L$865,Sales_Data!$B$2:$B$865,$A19,Sales_Data!$G$2:$G$865,$B19) -> 3294091.8 | H19: =SUMIFS(Sales_Data!$N$2:$N$865,Sales_Data!$B$2:$B$865,$A19,Sales_Data!$G$2:$G$865,$B19) -> 2907446.7 | I19: =G19-H19 -> 386645.11 | J19: =IF(G19=0,0,I19/G19) -> 0.11737533
A20: 2024 | B20: TAB-LITE-10 | C20: =INDEX(Master_Data!$B$2:$B$7,MATCH($B20,Master_Data!$A$2:$A$7,0)) -> LiteTab 10 Tablet | D20: =INDEX(Master_Data!$F$2:$F$7,MATCH($B20,Master_Data!$A$2:$A$7,0)) -> Growth | E20: =SUMIFS(Sales_Data!$H$2:$H$865,Sales_Data!$B$2:$B$865,$A20,Sales_Data!$G$2:$G$865,$B20) -> 11356 | F20: =SUMIFS(Sales_Data!$K$2:$K$865,Sales_Data!$B$2:$B$865,$A20,Sales_Data!$G$2:$G$865,$B20) -> 2595297.5 | G20: =SUMIFS(Sales_Data!$L$2:$L$865,Sales_Data!$B$2:$B$865,$A20,Sales_Data!$G$2:$G$865,$B20) -> 2324588.1 | H20: =SUMIFS(Sales_Data!$N$2:$N$865,Sales_Data!$B$2:$B$865,$A20,Sales_Data!$G$2:$G$865,$B20) -> 1792513.4 | I20: =G20-H20 -> 532074.66 | J20: =IF(G20=0,0,I20/G20) -> 0.22888987
A21: 2024 | B21: ACC-MSE-WL | C21: =INDEX(Master_Data!$B$2:$B$7,MATCH($B21,Master_Data!$A$2:$A$7,0)) -> Wireless Mouse | D21: =INDEX(Master_Data!$F$2:$F$7,MATCH($B21,Master_Data!$A$2:$A$7,0)) -> Mature | E21: =SUMIFS(Sales_Data!$H$2:$H$865,Sales_Data!$B$2:$B$865,$A21,Sales_Data!$G$2:$G$865,$B21) -> 42147 | F21: =SUMIFS(Sales_Data!$K$2:$K$865,Sales_Data!$B$2:$B$865,$A21,Sales_Data!$G$2:$G$865,$B21) -> 481582.01 | G21: =SUMIFS(Sales_Data!$L$2:$L$865,Sales_Data!$B$2:$B$865,$A21,Sales_Data!$G$2:$G$865,$B21) -> 431450.7 | H21: =SUMIFS(Sales_Data!$N$2:$N$865,Sales_Data!$B$2:$B$865,$A21,Sales_Data!$G$2:$G$865,$B21) -> 245270.28 | I21: =G21-H21 -> 186180.42 | J21: =IF(G21=0,0,I21/G21) -> 0.43152189
A22: 2024 | B22: SW-OFF-365 | C22: =INDEX(Master_Data!$B$2:$B$7,MATCH($B22,Master_Data!$A$2:$A$7,0)) -> Office Software Bundle | D22: =INDEX(Master_Data!$F$2:$F$7,MATCH($B22,Master_Data!$A$2:$A$7,0)) -> Growth | E22: =SUMIFS(Sales_Data!$H$2:$H$865,Sales_Data!$B$2:$B$865,$A22,Sales_Data!$G$2:$G$865,$B22) -> 12876 | F22: =SUMIFS(Sales_Data!$K$2:$K$865,Sales_Data!$B$2:$B$865,$A22,Sales_Data!$G$2:$G$865,$B22) -> 893398.78 | G22: =SUMIFS(Sales_Data!$L$2:$L$865,Sales_Data!$B$2:$B$865,$A22,Sales_Data!$G$2:$G$865,$B22) -> 813676.47 | H22: =SUMIFS(Sales_Data!$N$2:$N$865,Sales_Data!$B$2:$B$865,$A22,Sales_Data!$G$2:$G$865,$B22) -> 192547.05 | I22: =G22-H22 -> 621129.42 | J22: =IF(G22=0,0,I22/G22) -> 0.76336166
A23: 2024 | B23: WAR-EXT-2Y | C23: =INDEX(Master_Data!$B$2:$B$7,MATCH($B23,Master_Data!$A$2:$A$7,0)) -> Extended Warranty 2Y | D23: =INDEX(Master_Data!$F$2:$F$7,MATCH($B23,Master_Data!$A$2:$A$7,0)) -> Mature | E23: =SUMIFS(Sales_Data!$H$2:$H$865,Sales_Data!$B$2:$B$865,$A23,Sales_Data!$G$2:$G$865,$B23) -> 9601 | F23: =SUMIFS(Sales_Data!$K$2:$K$865,Sales_Data!$B$2:$B$865,$A23,Sales_Data!$G$2:$G$865,$B23) -> 509307.38 | G23: =SUMIFS(Sales_Data!$L$2:$L$865,Sales_Data!$B$2:$B$865,$A23,Sales_Data!$G$2:$G$865,$B23) -> 477036.37 | H23: =SUMIFS(Sales_Data!$N$2:$N$865,Sales_Data!$B$2:$B$865,$A23,Sales_Data!$G$2:$G$865,$B23) -> 71748.31 | I23: =G23-H23 -> 405288.06 | J23: =IF(G23=0,0,I23/G23) -> 0.84959572
... A29: 2025 | B29: WAR-EXT-2Y | C29: =INDEX(Master_Data!$B$2:$B$7,MATCH($B29,Master_Data!$A$2:$A$7,0)) -> Extended Warranty 2Y | D29: =INDEX(Master_Data!$F$2:$F$7,MATCH($B29,Master_Data!$A$2:$A$7,0)) -> Mature | E29: =SUMIFS(Sales_Data!$H$2:$H$865,Sales_Data!$B$2:$B$865,$A29,Sales_Data!$G$2:$G$865,$B29) -> 10757 | F29: =SUMIFS(Sales_Data!$K$2:$K$865,Sales_Data!$B$2:$B$865,$A29,Sales_Data!$G$2:$G$865,$B29) -> 585721.44 | G29: =SUMIFS(Sales_Data!$L$2:$L$865,Sales_Data!$B$2:$B$865,$A29,Sales_Data!$G$2:$G$865,$B29) -> 548580.81 | H29: =SUMIFS(Sales_Data!$N$2:$N$865,Sales_Data!$B$2:$B$865,$A29,Sales_Data!$G$2:$G$865,$B29) -> 84406.37 | I29: =G29-H29 -> 464174.44 | J29: =IF(G29=0,0,I29/G29) -> 0.84613685

Sheet 2_2026_Forecast
A1: Vantage Tech Supplies Ltd — 2026 Scenario Forecast
A2: UK Region | Pick a scenario below to flex the whole forecast
A4: Select scenario: | B4: Margin Recovery | C4: ← choose one of the 5 scenarios; all figures below update automatically
A6: 2026F Net Revenue | C6: 2026F Gross Margin | E6: 2026F Gross Margin % | G6: GM% vs 2025 Actual
A7: =INDEX(Forecast_2026!$D$37:$D$41,MATCH($B$4,Forecast_2026!$A$37:$A$41,0)) -> 14145686 | C7: =INDEX(Forecast_2026!$F$37:$F$41,MATCH($B$4,Forecast_2026!$A$37:$A$41,0)) -> 3694502.3 | E7: =INDEX(Forecast_2026!$G$37:$G$41,MATCH($B$4,Forecast_2026!$A$37:$A$41,0)) -> 0.2611752 | G7: =E7-Actuals_Summary!$G$7 -> 0.031308433
A9: Net revenue, gross margin & GM% — 2023-2026F
A10: Year | B10: Net_Revenue | C10: Gross_Margin | D10: Gross_Margin_%
A11: 2023 | B11: =INDEX(Actuals_Summary!$D$5:$D$7,MATCH($A11,Actuals_Summary!$A$5:$A$7,0)) -> 9095479.6 | C11: =INDEX(Actuals_Summary!$F$5:$F$7,MATCH($A11,Actuals_Summary!$A$5:$A$7,0)) -> 2375545.5 | D11: =INDEX(Actuals_Summary!$G$5:$G$7,MATCH($A11,Actuals_Summary!$A$5:$A$7,0)) -> 0.26117869
A12: 2024 | B12: =INDEX(Actuals_Summary!$D$5:$D$7,MATCH($A12,Actuals_Summary!$A$5:$A$7,0)) -> 10782900 | C12: =INDEX(Actuals_Summary!$F$5:$F$7,MATCH($A12,Actuals_Summary!$A$5:$A$7,0)) -> 2665259.9 | D12: =INDEX(Actuals_Summary!$G$5:$G$7,MATCH($A12,Actuals_Summary!$A$5:$A$7,0)) -> 0.24717468
A13: 2025 | B13: =INDEX(Actuals_Summary!$D$5:$D$7,MATCH($A13,Actuals_Summary!$A$5:$A$7,0)) -> 12796433 | C13: =INDEX(Actuals_Summary!$F$5:$F$7,MATCH($A13,Actuals_Summary!$A$5:$A$7,0)) -> 2941474.7 | D13: =INDEX(Actuals_Summary!$G$5:$G$7,MATCH($A13,Actuals_Summary!$A$5:$A$7,0)) -> 0.22986677
A14: 2026F | B14: =INDEX(Forecast_2026!$D$37:$D$41,MATCH($B$4,Forecast_2026!$A$37:$A$41,0)) -> 14145686 | C14: =INDEX(Forecast_2026!$F$37:$F$41,MATCH($B$4,Forecast_2026!$A$37:$A$41,0)) -> 3694502.3 | D14: =INDEX(Forecast_2026!$G$37:$G$41,MATCH($B$4,Forecast_2026!$A$37:$A$41,0)) -> 0.2611752
A16: All scenarios — 2026 forecast comparison
A17: Scenario | B17: Net_Revenue_2026 | C17: Gross_Margin_2026 | D17: Gross_Margin_%_2026 | E17: Marketing_Spend_2026 | F17: Rev_vs_2025 | G17: GM%_vs_2025_pp
A18: =Forecast_2026!A37 -> Base Case | B18: =Forecast_2026!D37 -> 14096551 | C18: =Forecast_2026!F37 -> 3027461.5 | D18: =Forecast_2026!G37 -> 0.21476611 | E18: =Forecast_2026!H37 -> 245460.02 | F18: =B18/Actuals_Summary!$D$7-1 -> 0.1016 | G18: =D18-Actuals_Summary!$G$7 -> -0.015100652
A19: =Forecast_2026!A38 -> Optimistic | B19: =Forecast_2026!D38 -> 15339366 | C19: =Forecast_2026!F38 -> 3880020.7 | D19: =Forecast_2026!G38 -> 0.2529453 | E19: =Forecast_2026!H38 -> 257148.6 | F19: =B19/Actuals_Summary!$D$7-1 -> 0.19872203 | G19: =D19-Actuals_Summary!$G$7 -> 0.023078536
A20: =Forecast_2026!A39 -> Pessimistic | B20: =Forecast_2026!D39 -> 12763439 | C20: =Forecast_2026!F39 -> 1907216.7 | D20: =Forecast_2026!G39 -> 0.14942812 | E20: =Forecast_2026!H39 -> 222082.88 | F20: =B20/Actuals_Summary!$D$7-1 -> -0.0025783935 | G20: =D20-Actuals_Summary!$G$7 -> -0.080438646
A21: =Forecast_2026!A40 -> Margin Recovery | B21: =Forecast_2026!D40 -> 14145686 | C21: =Forecast_2026!F40 -> 3694502.3 | D21: =Forecast_2026!G40 -> 0.2611752 | E21: =Forecast_2026!H40 -> 233771.45 | F21: =B21/Actuals_Summary!$D$7-1 -> 0.10543974 | G21: =D21-Actuals_Summary!$G$7 -> 0.031308433
A22: =Forecast_2026!A41 -> Growth Push | B22: =Forecast_2026!D41 -> 14744409 | C22: =Forecast_2026!F41 -> 2534115.7 | D22: =Forecast_2026!G41 -> 0.1718696 | E22: =Forecast_2026!H41 -> 280525.74 | F22: =B22/Actuals_Summary!$D$7-1 -> 0.15222805 | G22: =D22-Actuals_Summary!$G$7 -> -0.05799717

Sheet Forecast_2026
A1: Vantage Tech Supplies Ltd — 2026 Scenario Forecast (SKU level)
A3: Scenario | B3: SKU_ID | C3: Product_Name | D3: Lifecycle_Stage | E3: Base_Units_2025 | F3: Base_Price_2025 | G3: Base_UnitCost_2025 | H3: Base_Discount_2025 | I3: Base_Marketing_2025 | J3: Unit_Growth_% | K3: Price_Change_% | L3: Cost_Inflation_% | M3: Discount_Change_pp | N3: Marketing_Change_% | O3: Units_2026 | P3: Price_2026 | Q3: UnitCost_2026 | R3: Discount_2026 | S3: Gross_Revenue_2026 | T3: Net_Revenue_2026 | U3: COGS_2026 | V3: Gross_Margin_2026 | W3: Gross_Margin_%_2026 | X3: Marketing_2026
A4: Base Case | B4: LAP-AIR-13 | C4: =INDEX(Master_Data!$B$2:$B$7,MATCH($B4,Master_Data!$A$2:$A$7,0)) -> AeroBook 13 Laptop | D4: =INDEX(Master_Data!$F$2:$F$7,MATCH($B4,Master_Data!$A$2:$A$7,0)) -> Growth | E4: =SUMIFS(Sales_Data!$H$2:$H$865,Sales_Data!$B$2:$B$865,2025,Sales_Data!$G$2:$G$865,$B4) -> 8883 | F4: =IFERROR(SUMIFS(Sales_Data!$K$2:$K$865,Sales_Data!$B$2:$B$865,2025,Sales_Data!$G$2:$G$865,$B4)/E4,0) -> 519.44022 | G4: =IFERROR(SUMIFS(Sales_Data!$N$2:$N$865,Sales_Data!$B$2:$B$865,2025,Sales_Data!$G$2:$G$865,$B4)/E4,0) -> 405.5295 | H4: =IFERROR(1-SUMIFS(Sales_Data!$L$2:$L$865,Sales_Data!$B$2:$B$865,2025,Sales_Data!$G$2:$G$865,$B4)/SUMIFS(Sales_Data!$K$2:$K$865,Sales_Data!$B$2:$B$865,2025,Sales_Data!$G$2:$G$865,$B4),0) -> 0.096453678 | I4: =SUMIFS(Sales_Data!$Q$2:$Q$865,Sales_Data!$B$2:$B$865,2025,Sales_Data!$G$2:$G$865,$B4) -> 60635.43 | J4: =INDEX(Assumed_scenario!$B$2:$B$6,MATCH($A4,Assumed_scenario!$A$2:$A$6,0)) -> 0.08 | K4: =INDEX(Assumed_scenario!$C$2:$C$6,MATCH($A4,Assumed_scenario!$A$2:$A$6,0)) -> 0.02 | L4: =INDEX(Assumed_scenario!$D$2:$D$6,MATCH($A4,Assumed_scenario!$A$2:$A$6,0)) -> 0.04 | M4: =INDEX(Assumed_scenario!$E$2:$E$6,MATCH($A4,Assumed_scenario!$A$2:$A$6,0)) -> 0 | N4: =INDEX(Assumed_scenario!$F$2:$F$6,MATCH($A4,Assumed_scenario!$A$2:$A$6,0)) -> 0.05 | O4: =E4*(1+J4) -> 9593.64 | P4: =F4*(1+K4) -> 529.82902 | Q4: =G4*(1+L4) -> 421.75068 | R4: =MAX(0,H4+M4) -> 0.096453678 | S4: =O4*P4 -> 5082988.9 | T4: =S4*(1-R4) -> 4592715.9 | U4: =O4*Q4 -> 4046124.2 | V4: =T4-U4 -> 546591.67 | W4: =IF(T4=0,0,V4/T4) -> 0.11901273 | X4: =I4*(1+N4) -> 63667.202
A5: Base Case | B5: LAP-PRO-15 | C5: =INDEX(Master_Data!$B$2:$B$7,MATCH($B5,Master_Data!$A$2:$A$7,0)) -> ProBook 15 Laptop | D5: =INDEX(Master_Data!$F$2:$F$7,MATCH($B5,Master_Data!$A$2:$A$7,0)) -> Mature | E5: =SUMIFS(Sales_Data!$H$2:$H$865,Sales_Data!$B$2:$B$865,2025,Sales_Data!$G$2:$G$865,$B5) -> 5711 | F5: =IFERROR(SUMIFS(Sales_Data!$K$2:$K$865,Sales_Data!$B$2:$B$865,2025,Sales_Data!$G$2:$G$865,$B5)/E5,0) -> 737.11291 | G5: =IFERROR(SUMIFS(Sales_Data!$N$2:$N$865,Sales_Data!$B$2:$B$865,2025,Sales_Data!$G$2:$G$865,$B5)/E5,0) -> 601.75935 | H5: =IFERROR(1-SUMIFS(Sales_Data!$L$2:$L$865,Sales_Data!$B$2:$B$865,2025,Sales_Data!$G$2:$G$865,$B5)/SUMIFS(Sales_Data!$K$2:$K$865,Sales_Data!$B$2:$B$865,2025,Sales_Data!$G$2:$G$865,$B5),0) -> 0.095687189 | I5: =SUMIFS(Sales_Data!$Q$2:$Q$865,Sales_Data!$B$2:$B$865,2025,Sales_Data!$G$2:$G$865,$B5) -> 60576.5 | J5: =INDEX(Assumed_scenario!$B$2:$B$6,MATCH($A5,Assumed_scenario!$A$2:$A$6,0)) -> 0.08 | K5: =INDEX(Assumed_scenario!$C$2:$C$6,MATCH($A5,Assumed_scenario!$A$2:$A$6,0)) -> 0.02 | L5: =INDEX(Assumed_scenario!$D$2:$D$6,MATCH($A5,Assumed_scenario!$A$2:$A$6,0)) -> 0.04 | M5: =INDEX(Assumed_scenario!$E$2:$E$6,MATCH($A5,Assumed_scenario!$A$2:$A$6,0)) -> 0 | N5: =INDEX(Assumed_scenario!$F$2:$F$6,MATCH($A5,Assumed_scenario!$A$2:$A$6,0)) -> 0.05 | O5: =E5*(1+J5) -> 6167.88 | P5: =F5*(1+K5) -> 751.85517 | Q5: =G5*(1+L5) -> 625.82973 | R5: =MAX(0,H5+M5) -> 0.095687189 | S5: =O5*P5 -> 4637352.4 | T5: =S5*(1-R5) -> 4193617.2 | U5: =O5*Q5 -> 3860042.7 | V5: =T5-U5 -> 333574.57 | W5: =IF(T5=0,0,V5/T5) -> 0.0795434 | X5: =I5*(1+N5) -> 63605.325
A6: Base Case | B6: TAB-LITE-10 | C6: =INDEX(Master_Data!$B$2:$B$7,MATCH($B6,Master_Data!$A$2:$A$7,0)) -> LiteTab 10 Tablet | D6: =INDEX(Master_Data!$F$2:$F$7,MATCH($B6,Master_Data!$A$2:$A$7,0)) -> Growth | E6: =SUMIFS(Sales_Data!$H$2:$H$865,Sales_Data!$B$2:$B$865,2025,Sales_Data!$G$2:$G$865,$B6) -> 13300 | F6: =IFERROR(SUMIFS(Sales_Data!$K$2:$K$865,Sales_Data!$B$2:$B$865,2025,Sales_Data!$G$2:$G$865,$B6)/E6,0) -> 234.55276 | G6: =IFERROR(SUMIFS(Sales_Data!$N$2:$N$865,Sales_Data!$B$2:$B$865,2025,Sales_Data!$G$2:$G$865,$B6)/E6,0) -> 165.70185 | H6: =IFERROR(1-SUMIFS(Sales_Data!$L$2:$L$865,Sales_Data!$B$2:$B$865,2025,Sales_Data!$G$2:$G$865,$B6)/SUMIFS(Sales_Data!$K$2:$K$865,Sales_Data!$B$2:$B$865,2025,Sales_Data!$G$2:$G$865,$B6),0) -> 0.10485974 | I6: =SUMIFS(Sales_Data!$Q$2:$Q$865,Sales_Data!$B$2:$B$865,2025,Sales_Data!$G$2:$G$865,$B6) -> 43839.35 | J6: =INDEX(Assumed_scenario!$B$2:$B$6,MATCH($A6,Assumed_scenario!$A$2:$A$6,0)) -> 0.08 | K6: =INDEX(Assumed_scenario!$C$2:$C$6,MATCH($A6,Assumed_scenario!$A$2:$A$6,0)) -> 0.02 | L6: =INDEX(Assumed_scenario!$D$2:$D$6,MATCH($A6,Assumed_scenario!$A$2:$A$6,0)) -> 0.04 | M6: =INDEX(Assumed_scenario!$E$2:$E$6,MATCH($A6,Assumed_scenario!$A$2:$A$6,0)) -> 0 | N6: =INDEX(Assumed_scenario!$F$2:$F$6,MATCH($A6,Assumed_scenario!$A$2:$A$6,0)) -> 0.05 | O6: =E6*(1+J6) -> 14364 | P6: =F6*(1+K6) -> 239.24382 | Q6: =G6*(1+L6) -> 172.32992 | R6: =MAX(0,H6+M6) -> 0.10485974 | S6: =O6*P6 -> 3436498.2 | T6: =S6*(1-R6) -> 3076147.9 | U6: =O6*Q6 -> 2475347 | V6: =T6-U6 -> 600800.87 | W6: =IF(T6=0,0,V6/T6) -> 0.19530949 | X6: =I6*(1+N6) -> 46031.317
A7: Base Case | B7: ACC-MSE-WL | C7: =INDEX(Master_Data!$B$2:$B$7,MATCH($B7,Master_Data!$A$2:$A$7,0)) -> Wireless Mouse | D7: =INDEX(Master_Data!$F$2:$F$7,MATCH($B7,Master_Data!$A$2:$A$7,0)) -> Mature | E7: =SUMIFS(Sales_Data!$H$2:$H$865,Sales_Data!$B$2:$B$865,2025,Sales_Data!$G$2:$G$865,$B7) -> 47593 | F7: =IFERROR(SUMIFS(Sales_Data!$K$2:$K$865,Sales_Data!$B$2:$B$865,2025,Sales_Data!$G$2:$G$865,$B7)/E7,0) -> 11.72735 | G7: =IFERROR(SUMIFS(Sales_Data!$N$2:$N$865,Sales_Data!$B$2:$B$865,2025,Sales_Data!$G$2:$G$865,$B7)/E7,0) -> 6.1056006 | H7: =IFERROR(1-SUMIFS(Sales_Data!$L$2:$L$865,Sales_Data!$B$2:$B$865,2025,Sales_Data!$G$2:$G$865,$B7)/SUMIFS(Sales_Data!$K$2:$K$865,Sales_Data!$B$2:$B$865,2025,Sales_Data!$G$2:$G$865,$B7),0) -> 0.10439855 | I7: =SUMIFS(Sales_Data!$Q$2:$Q$865,Sales_Data!$B$2:$B$865,2025,Sales_Data!$G$2:$G$865,$B7) -> 20847.37 | J7: =INDEX(Assumed_scenario!$B$2:$B$6,MATCH($A7,Assumed_scenario!$A$2:$A$6,0)) -> 0.08 | K7: =INDEX(Assumed_scenario!$C$2:$C$6,MATCH($A7,Assumed_scenario!$A$2:$A$6,0)) -> 0.02 | L7: =INDEX(Assumed_scenario!$D$2:$D$6,MATCH($A7,Assumed_scenario!$A$2:$A$6,0)) -> 0.04 | M7: =INDEX(Assumed_scenario!$E$2:$E$6,MATCH($A7,Assumed_scenario!$A$2:$A$6,0)) -> 0 | N7: =INDEX(Assumed_scenario!$F$2:$F$6,MATCH($A7,Assumed_scenario!$A$2:$A$6,0)) -> 0.05 | O7: =E7*(1+J7) -> 51400.44 | P7: =F7*(1+K7) -> 11.961897 | Q7: =G7*(1+L7) -> 6.3498246 | R7: =MAX(0,H7+M7) -> 0.10439855 | S7: =O7*P7 -> 614846.77 | T7: =S7*(1-R7) -> 550657.66 | U7: =O7*Q7 -> 326383.78 | V7: =T7-U7 -> 224273.88 | W7: =IF(T7=0,0,V7/T7) -> 0.40728369 | X7: =I7*(1+N7) -> 21889.739
A8: Base Case | B8: SW-OFF-365 | C8: =INDEX(Master_Data!$B$2:$B$7,MATCH($B8,Master_Data!$A$2:$A$7,0)) -> Office Software Bundle | D8: =INDEX(Master_Data!$F$2:$F$7,MATCH($B8,Master_Data!$A$2:$A$7,0)) -> Growth | E8: =SUMIFS(Sales_Data!$H$2:$H$865,Sales_Data!$B$2:$B$865,2025,Sales_Data!$G$2:$G$865,$B8) -> 15105 | F8: =IFERROR(SUMIFS(Sales_Data!$K$2:$K$865,Sales_Data!$B$2:$B$865,2025,Sales_Data!$G$2:$G$865,$B8)/E8,0) -> 71.210546 | G8: =IFERROR(SUMIFS(Sales_Data!$N$2:$N$865,Sales_Data!$B$2:$B$865,2025,Sales_Data!$G$2:$G$865,$B8)/E8,0) -> 15.701255 | H8: =IFERROR(1-SUMIFS(Sales_Data!$L$2:$L$865,Sales_Data!$B$2:$B$865,2025,Sales_Data!$G$2:$G$865,$B8)/SUMIFS(Sales_Data!$K$2:$K$865,Sales_Data!$B$2:$B$865,2025,Sales_Data!$G$2:$G$865,$B8),0) -> 0.08930923 | I8: =SUMIFS(Sales_Data!$Q$2:$Q$865,Sales_Data!$B$2:$B$865,2025,Sales_Data!$G$2:$G$865,$B8) -> 28662.93 | J8: =INDEX(Assumed_scenario!$B$2:$B$6,MATCH($A8,Assumed_scenario!$A$2:$A$6,0)) -> 0.08 | K8: =INDEX(Assumed_scenario!$C$2:$C$6,MATCH($A8,Assumed_scenario!$A$2:$A$6,0)) -> 0.02 | L8: =INDEX(Assumed_scenario!$D$2:$D$6,MATCH($A8,Assumed_scenario!$A$2:$A$6,0)) -> 0.04 | M8: =INDEX(Assumed_scenario!$E$2:$E$6,MATCH($A8,Assumed_scenario!$A$2:$A$6,0)) -> 0 | N8: =INDEX(Assumed_scenario!$F$2:$F$6,MATCH($A8,Assumed_scenario!$A$2:$A$6,0)) -> 0.05 | O8: =E8*(1+J8) -> 16313.4 | P8: =F8*(1+K8) -> 72.634757 | Q8: =G8*(1+L8) -> 16.329305 | R8: =MAX(0,H8+M8) -> 0.08930923 | S8: =O8*P8 -> 1184919.8 | T8: =S8*(1-R8) -> 1079095.6 | U8: =O8*Q8 -> 266386.49 | V8: =T8-U8 -> 812709.08 | W8: =IF(T8=0,0,V8/T8) -> 0.75313911 | X8: =I8*(1+N8) -> 30096.077
A9: Base Case | B9: WAR-EXT-2Y | C9: =INDEX(Master_Data!$B$2:$B$7,MATCH($B9,Master_Data!$A$2:$A$7,0)) -> Extended Warranty 2Y | D9: =INDEX(Master_Data!$F$2:$F$7,MATCH($B9,Master_Data!$A$2:$A$7,0)) -> Mature | E9: =SUMIFS(Sales_Data!$H$2:$H$865,Sales_Data!$B$2:$B$865,2025,Sales_Data!$G$2:$G$865,$B9) -> 10757 | F9: =IFERROR(SUMIFS(Sales_Data!$K$2:$K$865,Sales_Data!$B$2:$B$865,2025,Sales_Data!$G$2:$G$865,$B9)/E9,0) -> 54.450259 | G9: =IFERROR(SUMIFS(Sales_Data!$N$2:$N$865,Sales_Data!$B$2:$B$865,2025,Sales_Data!$G$2:$G$865,$B9)/E9,0) -> 7.8466459 | H9: =IFERROR(1-SUMIFS(Sales_Data!$L$2:$L$865,Sales_Data!$B$2:$B$865,2025,Sales_Data!$G$2:$G$865,$B9)/SUMIFS(Sales_Data!$K$2:$K$865,Sales_Data!$B$2:$B$865,2025,Sales_Data!$G$2:$G$865,$B9),0) -> 0.063410057 | I9: =SUMIFS(Sales_Data!$Q$2:$Q$865,Sales_Data!$B$2:$B$865,2025,Sales_Data!$G$2:$G$865,$B9) -> 19209.87 | J9: =INDEX(Assumed_scenario!$B$2:$B$6,MATCH($A9,Assumed_scenario!$A$2:$A$6,0)) -> 0.08 | K9: =INDEX(Assumed_scenario!$C$2:$C$6,MATCH($A9,Assumed_scenario!$A$2:$A$6,0)) -> 0.02 | L9: =INDEX(Assumed_scenario!$D$2:$D$6,MATCH($A9,Assumed_scenario!$A$2:$A$6,0)) -> 0.04 | M9: =INDEX(Assumed_scenario!$E$2:$E$6,MATCH($A9,Assumed_scenario!$A$2:$A$6,0)) -> 0 | N9: =INDEX(Assumed_scenario!$F$2:$F$6,MATCH($A9,Assumed_scenario!$A$2:$A$6,0)) -> 0.05 | O9: =E9*(1+J9) -> 11617.56 | P9: =F9*(1+K9) -> 55.539265 | Q9: =G9*(1+L9) -> 8.1605117 | R9: =MAX(0,H9+M9) -> 0.063410057 | S9: =O9*P9 -> 645230.74 | T9: =S9*(1-R9) -> 604316.62 | U9: =O9*Q9 -> 94805.235 | V9: =T9-U9 -> 509511.39 | W9: =IF(T9=0,0,V9/T9) -> 0.84311993 | X9: =I9*(1+N9) -> 20170.363
A10: Optimistic | B10: LAP-AIR-13 | C10: =INDEX(Master_Data!$B$2:$B$7,MATCH($B10,Master_Data!$A$2:$A$7,0)) -> AeroBook 13 Laptop | D10: =INDEX(Master_Data!$F$2:$F$7,MATCH($B10,Master_Data!$A$2:$A$7,0)) -> Growth | E10: =SUMIFS(Sales_Data!$H$2:$H$865,Sales_Data!$B$2:$B$865,2025,Sales_Data!$G$2:$G$865,$B10) -> 8883 | F10: =IFERROR(SUMIFS(Sales_Data!$K$2:$K$865,Sales_Data!$B$2:$B$865,2025,Sales_Data!$G$2:$G$865,$B10)/E10,0) -> 519.44022 | G10: =IFERROR(SUMIFS(Sales_Data!$N$2:$N$865,Sales_Data!$B$2:$B$865,2025,Sales_Data!$G$2:$G$865,$B10)/E10,0) -> 405.5295 | H10: =IFERROR(1-SUMIFS(Sales_Data!$L$2:$L$865,Sales_Data!$B$2:$B$865,2025,Sales_Data!$G$2:$G$865,$B10)/SUMIFS(Sales_Data!$K$2:$K$865,Sales_Data!$B$2:$B$865,2025,Sales_Data!$G$2:$G$865,$B10),0) -> 0.096453678 | I10: =SUMIFS(Sales_Data!$Q$2:$Q$865,Sales_Data!$B$2:$B$865,2025,Sales_Data!$G$2:$G$865,$B10) -> 60635.43 | J10: =INDEX(Assumed_scenario!$B$2:$B$6,MATCH($A10,Assumed_scenario!$A$2:$A$6,0)) -> 0.14 | K10: =INDEX(Assumed_scenario!$C$2:$C$6,MATCH($A10,Assumed_scenario!$A$2:$A$6,0)) -> 0.04 | L10: =INDEX(Assumed_scenario!$D$2:$D$6,MATCH($A10,Assumed_scenario!$A$2:$A$6,0)) -> 0.02 | M10: =INDEX(Assumed_scenario!$E$2:$E$6,MATCH($A10,Assumed_scenario!$A$2:$A$6,0)) -> -0.01 | N10: =INDEX(Assumed_scenario!$F$2:$F$6,MATCH($A10,Assumed_scenario!$A$2:$A$6,0)) -> 0.1 | O10: =E10*(1+J10) -> 10126.62 | P10: =F10*(1+K10) -> 540.21782 | Q10: =G10*(1+L10) -> 413.64009 | R10: =MAX(0,H10+M10) -> 0.086453678 | S10: =O10*P10 -> 5470580.6 | T10: =S10*(1-R10) -> 4997628.8 | U10: =O10*Q10 -> 4188776 | V10: =T10-U10 -> 808852.76 | W10: =IF(T10=0,0,V10/T10) -> 0.16184731 | X10: =I10*(1+N10) -> 66698.973
A11: Optimistic | B11: LAP-PRO-15 | C11: =INDEX(Master_Data!$B$2:$B$7,MATCH($B11,Master_Data!$A$2:$A$7,0)) -> ProBook 15 Laptop | D11: =INDEX(Master_Data!$F$2:$F$7,MATCH($B11,Master_Data!$A$2:$A$7,0)) -> Mature | E11: =SUMIFS(Sales_Data!$H$2:$H$865,Sales_Data!$B$2:$B$865,2025,Sales_Data!$G$2:$G$865,$B11) -> 5711 | F11: =IFERROR(SUMIFS(Sales_Data!$K$2:$K$865,Sales_Data!$B$2:$B$865,2025,Sales_Data!$G$2:$G$865,$B11)/E11,0) -> 737.11291 | G11: =IFERROR(SUMIFS(Sales_Data!$N$2:$N$865,Sales_Data!$B$2:$B$865,2025,Sales_Data!$G$2:$G$865,$B11)/E11,0) -> 601.75935 | H11: =IFERROR(1-SUMIFS(Sales_Data!$L$2:$L$865,Sales_Data!$B$2:$B$865,2025,Sales_Data!$G$2:$G$865,$B11)/SUMIFS(Sales_Data!$K$2:$K$865,Sales_Data!$B$2:$B$865,2025,Sales_Data!$G$2:$G$865,$B11),0) -> 0.095687189 | I11: =SUMIFS(Sales_Data!$Q$2:$Q$865,Sales_Data!$B$2:$B$865,2025,Sales_Data!$G$2:$G$865,$B11) -> 60576.5 | J11: =INDEX(Assumed_scenario!$B$2:$B$6,MATCH($A11,Assumed_scenario!$A$2:$A$6,0)) -> 0.14 | K11: =INDEX(Assumed_scenario!$C$2:$C$6,MATCH($A11,Assumed_scenario!$A$2:$A$6,0)) -> 0.04 | L11: =INDEX(Assumed_scenario!$D$2:$D$6,MATCH($A11,Assumed_scenario!$A$2:$A$6,0)) -> 0.02 | M11: =INDEX(Assumed_scenario!$E$2:$E$6,MATCH($A11,Assumed_scenario!$A$2:$A$6,0)) -> -0.01 | N11: =INDEX(Assumed_scenario!$F$2:$F$6,MATCH($A11,Assumed_scenario!$A$2:$A$6,0)) -> 0.1 | O11: =E11*(1+J11) -> 6510.54 | P11: =F11*(1+K11) -> 766.59742 | Q11: =G11*(1+L11) -> 613.79454 | R11: =MAX(0,H11+M11) -> 0.085687189 | S11: =O11*P11 -> 4990963.2 | T11: =S11*(1-R11) -> 4563301.6 | U11: =O11*Q11 -> 3996133.9 | V11: =T11-U11 -> 567167.69 | W11: =IF(T11=0,0,V11/T11) -> 0.12428889 | X11: =I11*(1+N11) -> 66634.15
A12: Optimistic | B12: TAB-LITE-10 | C12: =INDEX(Master_Data!$B$2:$B$7,MATCH($B12,Master_Data!$A$2:$A$7,0)) -> LiteTab 10 Tablet | D12: =INDEX(Master_Data!$F$2:$F$7,MATCH($B12,Master_Data!$A$2:$A$7,0)) -> Growth | E12: =SUMIFS(Sales_Data!$H$2:$H$865,Sales_Data!$B$2:$B$865,2025,Sales_Data!$G$2:$G$865,$B12) -> 13300 | F12: =IFERROR(SUMIFS(Sales_Data!$K$2:$K$865,Sales_Data!$B$2:$B$865,2025,Sales_Data!$G$2:$G$865,$B12)/E12,0) -> 234.55276 | G12: =IFERROR(SUMIFS(Sales_Data!$N$2:$N$865,Sales_Data!$B$2:$B$865,2025,Sales_Data!$G$2:$G$865,$B12)/E12,0) -> 165.70185 | H12: =IFERROR(1-SUMIFS(Sales_Data!$L$2:$L$865,Sales_Data!$B$2:$B$865,2025,Sales_Data!$G$2:$G$865,$B12)/SUMIFS(Sales_Data!$K$2:$K$865,Sales_Data!$B$2:$B$865,2025,Sales_Data!$G$2:$G$865,$B12),0) -> 0.10485974 | I12: =SUMIFS(Sales_Data!$Q$2:$Q$865,Sales_Data!$B$2:$B$865,2025,Sales_Data!$G$2:$G$865,$B12) -> 43839.35 | J12: =INDEX(Assumed_scenario!$B$2:$B$6,MATCH($A12,Assumed_scenario!$A$2:$A$6,0)) -> 0.14 | K12: =INDEX(Assumed_scenario!$C$2:$C$6,MATCH($A12,Assumed_scenario!$A$2:$A$6,0)) -> 0.04 | L12: =INDEX(Assumed_scenario!$D$2:$D$6,MATCH($A12,Assumed_scenario!$A$2:$A$6,0)) -> 0.02 | M12: =INDEX(Assumed_scenario!$E$2:$E$6,MATCH($A12,Assumed_scenario!$A$2:$A$6,0)) -> -0.01 | N12: =INDEX(Assumed_scenario!$F$2:$F$6,MATCH($A12,Assumed_scenario!$A$2:$A$6,0)) -> 0.1 | O12: =E12*(1+J12) -> 15162 | P12: =F12*(1+K12) -> 243.93487 | Q12: =G12*(1+L12) -> 169.01589 | R12: =MAX(0,H12+M12) -> 0.094859741 | S12: =O12*P12 -> 3698540.6 | T12: =S12*(1-R12) -> 3347698 | U12: =O12*Q12 -> 2562618.9 | V12: =T12-U12 -> 785079.08 | W12: =IF(T12=0,0,V12/T12) -> 0.23451312 | X12: =I12*(1+N12) -> 48223.285
A13: Optimistic | B13: ACC-MSE-WL | C13: =INDEX(Master_Data!$B$2:$B$7,MATCH($B13,Master_Data!$A$2:$A$7,0)) -> Wireless Mouse | D13: =INDEX(Master_Data!$F$2:$F$7,MATCH($B13,Master_Data!$A$2:$A$7,0)) -> Mature | E13: =SUMIFS(Sales_Data!$H$2:$H$865,Sales_Data!$B$2:$B$865,2025,Sales_Data!$G$2:$G$865,$B13) -> 47593 | F13: =IFERROR(SUMIFS(Sales_Data!$K$2:$K$865,Sales_Data!$B$2:$B$865,2025,Sales_Data!$G$2:$G$865,$B13)/E13,0) -> 11.72735 | G13: =IFERROR(SUMIFS(Sales_Data!$N$2:$N$865,Sales_Data!$B$2:$B$865,2025,Sales_Data!$G$2:$G$865,$B13)/E13,0) -> 6.1056006 | H13: =IFERROR(1-SUMIFS(Sales_Data!$L$2:$L$865,Sales_Data!$B$2:$B$865,2025,Sales_Data!$G$2:$G$865,$B13)/SUMIFS(Sales_Data!$K$2:$K$865,Sales_Data!$B$2:$B$865,2025,Sales_Data!$G$2:$G$865,$B13),0) -> 0.10439855 | I13: =SUMIFS(Sales_Data!$Q$2:$Q$865,Sales_Data!$B$2:$B$865,2025,Sales_Data!$G$2:$G$865,$B13) -> 20847.37 | J13: =INDEX(Assumed_scenario!$B$2:$B$6,MATCH($A13,Assumed_scenario!$A$2:$A$6,0)) -> 0.14 | K13: =INDEX(Assumed_scenario!$C$2:$C$6,MATCH($A13,Assumed_scenario!$A$2:$A$6,0)) -> 0.04 | L13: =INDEX(Assumed_scenario!$D$2:$D$6,MATCH($A13,Assumed_scenario!$A$2:$A$6,0)) -> 0.02 | M13: =INDEX(Assumed_scenario!$E$2:$E$6,MATCH($A13,Assumed_scenario!$A$2:$A$6,0)) -> -0.01 | N13: =INDEX(Assumed_scenario!$F$2:$F$6,MATCH($A13,Assumed_scenario!$A$2:$A$6,0)) -> 0.1 | O13: =E13*(1+J13) -> 54256.02 | P13: =F13*(1+K13) -> 12.196444 | Q13: =G13*(1+L13) -> 6.2277126 | R13: =MAX(0,H13+M13) -> 0.094398545 | S13: =O13*P13 -> 661730.51 | T13: =S13*(1-R13) -> 599264.11 | U13: =O13*Q13 -> 337890.9 | V13: =T13-U13 -> 261373.21 | W13: =IF(T13=0,0,V13/T13) -> 0.43615696 | X13: =I13*(1+N13) -> 22932.107
A14: Optimistic | B14: SW-OFF-365 | C14: =INDEX(Master_Data!$B$2:$B$7,MATCH($B14,Master_Data!$A$2:$A$7,0)) -> Office Software Bundle | D14: =INDEX(Master_Data!$F$2:$F$7,MATCH($B14,Master_Data!$A$2:$A$7,0)) -> Growth | E14: =SUMIFS(Sales_Data!$H$2:$H$865,Sales_Data!$B$2:$B$865,2025,Sales_Data!$G$2:$G$865,$B14) -> 15105 | F14: =IFERROR(SUMIFS(Sales_Data!$K$2:$K$865,Sales_Data!$B$2:$B$865,2025,Sales_Data!$G$2:$G$865,$B14)/E14,0) -> 71.210546 | G14: =IFERROR(SUMIFS(Sales_Data!$N$2:$N$865,Sales_Data!$B$2:$B$865,2025,Sales_Data!$G$2:$G$865,$B14)/E14,0) -> 15.701255 | H14: =IFERROR(1-SUMIFS(Sales_Data!$L$2:$L$865,Sales_Data!$B$2:$B$865,2025,Sales_Data!$G$2:$G$865,$B14)/SUMIFS(Sales_Data!$K$2:$K$865,Sales_Data!$B$2:$B$865,2025,Sales_Data!$G$2:$G$865,$B14),0) -> 0.08930923 | I14: =SUMIFS(Sales_Data!$Q$2:$Q$865,Sales_Data!$B$2:$B$865,2025,Sales_Data!$G$2:$G$865,$B14) -> 28662.93 | J14: =INDEX(Assumed_scenario!$B$2:$B$6,MATCH($A14,Assumed_scenario!$A$2:$A$6,0)) -> 0.14 | K14: =INDEX(Assumed_scenario!$C$2:$C$6,MATCH($A14,Assumed_scenario!$A$2:$A$6,0)) -> 0.04 | L14: =INDEX(Assumed_scenario!$D$2:$D$6,MATCH($A14,Assumed_scenario!$A$2:$A$6,0)) -> 0.02 | M14: =INDEX(Assumed_scenario!$E$2:$E$6,MATCH($A14,Assumed_scenario!$A$2:$A$6,0)) -> -0.01 | N14: =INDEX(Assumed_scenario!$F$2:$F$6,MATCH($A14,Assumed_scenario!$A$2:$A$6,0)) -> 0.1 | O14: =E14*(1+J14) -> 17219.7 | P14: =F14*(1+K14) -> 74.058968 | Q14: =G14*(1+L14) -> 16.01528 | R14: =MAX(0,H14+M14) -> 0.07930923 | S14: =O14*P14 -> 1275273.2 | T14: =S14*(1-R14) -> 1174132.3 | U14: =O14*Q14 -> 275778.32 | V14: =T14-U14 -> 898353.95 | W14: =IF(T14=0,0,V14/T14) -> 0.76512159 | X14: =I14*(1+N14) -> 31529.223
A15: Optimistic | B15: WAR-EXT-2Y | C15: =INDEX(Master_Data!$B$2:$B$7,MATCH($B15,Master_Data!$A$2:$A$7,0)) -> Extended Warranty 2Y | D15: =INDEX(Master_Data!$F$2:$F$7,MATCH($B15,Master_Data!$A$2:$A$7,0)) -> Mature | E15: =SUMIFS(Sales_Data!$H$2:$H$865,Sales_Data!$B$2:$B$865,2025,Sales_Data!$G$2:$G$865,$B15) -> 10757 | F15: =IFERROR(SUMIFS(Sales_Data!$K$2:$K$865,Sales_Data!$B$2:$B$865,2025,Sales_Data!$G$2:$G$865,$B15)/E15,0) -> 54.450259 | G15: =IFERROR(SUMIFS(Sales_Data!$N$2:$N$865,Sales_Data!$B$2:$B$865,2025,Sales_Data!$G$2:$G$865,$B15)/E15,0) -> 7.8466459 | H15: =IFERROR(1-SUMIFS(Sales_Data!$L$2:$L$865,Sales_Data!$B$2:$B$865,2025,Sales_Data!$G$2:$G$865,$B15)/SUMIFS(Sales_Data!$K$2:$K$865,Sales_Data!$B$2:$B$865,2025,Sales_Data!$G$2:$G$865,$B15),0) -> 0.063410057 | I15: =SUMIFS(Sales_Data!$Q$2:$Q$865,Sales_Data!$B$2:$B$865,2025,Sales_Data!$G$2:$G$865,$B15) -> 19209.87 | J15: =INDEX(Assumed_scenario!$B$2:$B$6,MATCH($A15,Assumed_scenario!$A$2:$A$6,0)) -> 0.14 | K15: =INDEX(Assumed_scenario!$C$2:$C$6,MATCH($A15,Assumed_scenario!$A$2:$A$6,0)) -> 0.04 | L15: =INDEX(Assumed_scenario!$D$2:$D$6,MATCH($A15,Assumed_scenario!$A$2:$A$6,0)) -> 0.02 | M15: =INDEX(Assumed_scenario!$E$2:$E$6,MATCH($A15,Assumed_scenario!$A$2:$A$6,0)) -> -0.01 | N15: =INDEX(Assumed_scenario!$F$2:$F$6,MATCH($A15,Assumed_scenario!$A$2:$A$6,0)) -> 0.1 | O15: =E15*(1+J15) -> 12262.98 | P15: =F15*(1+K15) -> 56.62827 | Q15: =G15*(1+L15) -> 8.0035788 | R15: =MAX(0,H15+M15) -> 0.053410057 | S15: =O15*P15 -> 694431.34 | T15: =S15*(1-R15) -> 657341.72 | U15: =O15*Q15 -> 98147.727 | V15: =T15-U15 -> 559193.99 | W15: =IF(T15=0,0,V15/T15) -> 0.85068995 | X15: =I15*(1+N15) -> 21130.857
... A33: Growth Push | B33: WAR-EXT-2Y | C33: =INDEX(Master_Data!$B$2:$B$7,MATCH($B33,Master_Data!$A$2:$A$7,0)) -> Extended Warranty 2Y | D33: =INDEX(Master_Data!$F$2:$F$7,MATCH($B33,Master_Data!$A$2:$A$7,0)) -> Mature | E33: =SUMIFS(Sales_Data!$H$2:$H$865,Sales_Data!$B$2:$B$865,2025,Sales_Data!$G$2:$G$865,$B33) -> 10757 | F33: =IFERROR(SUMIFS(Sales_Data!$K$2:$K$865,Sales_Data!$B$2:$B$865,2025,Sales_Data!$G$2:$G$865,$B33)/E33,0) -> 54.450259 | G33: =IFERROR(SUMIFS(Sales_Data!$N$2:$N$865,Sales_Data!$B$2:$B$865,2025,Sales_Data!$G$2:$G$865,$B33)/E33,0) -> 7.8466459 | H33: =IFERROR(1-SUMIFS(Sales_Data!$L$2:$L$865,Sales_Data!$B$2:$B$865,2025,Sales_Data!$G$2:$G$865,$B33)/SUMIFS(Sales_Data!$K$2:$K$865,Sales_Data!$B$2:$B$865,2025,Sales_Data!$G$2:$G$865,$B33),0) -> 0.063410057 | I33: =SUMIFS(Sales_Data!$Q$2:$Q$865,Sales_Data!$B$2:$B$865,2025,Sales_Data!$G$2:$G$865,$B33) -> 19209.87 | J33: =INDEX(Assumed_scenario!$B$2:$B$6,MATCH($A33,Assumed_scenario!$A$2:$A$6,0)) -> 0.18 | K33: =INDEX(Assumed_scenario!$C$2:$C$6,MATCH($A33,Assumed_scenario!$A$2:$A$6,0)) -> 0.01 | L33: =INDEX(Assumed_scenario!$D$2:$D$6,MATCH($A33,Assumed_scenario!$A$2:$A$6,0)) -> 0.05 | M33: =INDEX(Assumed_scenario!$E$2:$E$6,MATCH($A33,Assumed_scenario!$A$2:$A$6,0)) -> 0.03 | N33: =INDEX(Assumed_scenario!$F$2:$F$6,MATCH($A33,Assumed_scenario!$A$2:$A$6,0)) -> 0.2 | O33: =E33*(1+J33) -> 12693.26 | P33: =F33*(1+K33) -> 54.994762 | Q33: =G33*(1+L33) -> 8.2389782 | R33: =MAX(0,H33+M33) -> 0.093410057 | S33: =O33*P33 -> 698062.81 | T33: =S33*(1-R33) -> 632856.72 | U33: =O33*Q33 -> 104579.49 | V33: =T33-U33 -> 528277.23 | W33: =IF(T33=0,0,V33/T33) -> 0.83475013 | X33: =I33*(1+N33) -> 23051.844
A35: Scenario totals — 2026 forecast
A36: Scenario | B36: Units_2026 | C36: Gross_Revenue_2026 | D36: Net_Revenue_2026 | E36: COGS_2026 | F36: Gross_Margin_2026 | G36: Gross_Margin_%_2026 | H36: Marketing_2026
A37: Base Case | B37: =SUMIFS($O$4:$O$33,$A$4:$A$33,$A37) -> 109456.92 | C37: =SUMIFS($S$4:$S$33,$A$4:$A$33,$A37) -> 15601837 | D37: =SUMIFS($T$4:$T$33,$A$4:$A$33,$A37) -> 14096551 | E37: =SUMIFS($U$4:$U$33,$A$4:$A$33,$A37) -> 11069089 | F37: =SUMIFS($V$4:$V$33,$A$4:$A$33,$A37) -> 3027461.5 | G37: =IF(D37=0,0,F37/D37) -> 0.21476611 | H37: =SUMIFS($X$4:$X$33,$A$4:$A$33,$A37) -> 245460.02
A38: Optimistic | B38: =SUMIFS($O$4:$O$33,$A$4:$A$33,$A38) -> 115537.86 | C38: =SUMIFS($S$4:$S$33,$A$4:$A$33,$A38) -> 16791519 | D38: =SUMIFS($T$4:$T$33,$A$4:$A$33,$A38) -> 15339366 | E38: =SUMIFS($U$4:$U$33,$A$4:$A$33,$A38) -> 11459346 | F38: =SUMIFS($V$4:$V$33,$A$4:$A$33,$A38) -> 3880020.7 | G38: =IF(D38=0,0,F38/D38) -> 0.2529453 | H38: =SUMIFS($X$4:$X$33,$A$4:$A$33,$A38) -> 257148.6
A39: Pessimistic | B39: =SUMIFS($O$4:$O$33,$A$4:$A$33,$A39) -> 103375.98 | C39: =SUMIFS($S$4:$S$33,$A$4:$A$33,$A39) -> 14446145 | D39: =SUMIFS($T$4:$T$33,$A$4:$A$33,$A39) -> 12763439 | E39: =SUMIFS($U$4:$U$33,$A$4:$A$33,$A39) -> 10856222 | F39: =SUMIFS($V$4:$V$33,$A$4:$A$33,$A39) -> 1907216.7 | G39: =IF(D39=0,0,F39/D39) -> 0.14942812 | H39: =SUMIFS($X$4:$X$33,$A$4:$A$33,$A39) -> 222082.88
A40: Margin Recovery | B40: =SUMIFS($O$4:$O$33,$A$4:$A$33,$A40) -> 106416.45 | C40: =SUMIFS($S$4:$S$33,$A$4:$A$33,$A40) -> 15317163 | D40: =SUMIFS($T$4:$T$33,$A$4:$A$33,$A40) -> 14145686 | E40: =SUMIFS($U$4:$U$33,$A$4:$A$33,$A40) -> 10451184 | F40: =SUMIFS($V$4:$V$33,$A$4:$A$33,$A40) -> 3694502.3 | G40: =IF(D40=0,0,F40/D40) -> 0.2611752 | H40: =SUMIFS($X$4:$X$33,$A$4:$A$33,$A40) -> 233771.45
A41: Growth Push | B41: =SUMIFS($O$4:$O$33,$A$4:$A$33,$A41) -> 119591.82 | C41: =SUMIFS($S$4:$S$33,$A$4:$A$33,$A41) -> 16879329 | D41: =SUMIFS($T$4:$T$33,$A$4:$A$33,$A41) -> 14744409 | E41: =SUMIFS($U$4:$U$33,$A$4:$A$33,$A41) -> 12210294 | F41: =SUMIFS($V$4:$V$33,$A$4:$A$33,$A41) -> 2534115.7 | G41: =IF(D41=0,0,F41/D41) -> 0.1718696 | H41: =SUMIFS($X$4:$X$33,$A$4:$A$33,$A41) -> 280525.74

Sheet Sales_Data
A1: Period | B1: Year | C1: Month | D1: Region | E1: Channel | F1: Customer_Segment | G1: SKU_ID | H1: Units_Sold | I1: Avg_Selling_Price | J1: Discount_% | K1: Gross_Revenue | L1: Net_Revenue | M1: Unit_Cost | N1: Total_Cost | O1: Gross_Margin | P1: Gross_Margin_% | Q1: Marketing_Spend | R1: Promo_Flag
A2: 44927 | B2: 2023 | C2: Jan | D2: North | E2: Online | F2: Retail Customer | G2: LAP-AIR-13 | H2: 114 | I2: 490.44 | J2: 0.085 | K2: 55909.65 | L2: 51157.33 | M2: 369.68 | N2: 42142.95 | O2: 9014.38 | P2: 0.1762 | Q2: 1035.57 | R2: No
A3: 44927 | B3: 2023 | C3: Jan | D3: South | E3: Retail | F3: Student | G3: LAP-AIR-13 | H3: 98 | I3: 495.36 | J3: 0.055 | K3: 48545.72 | L3: 45875.71 | M3: 369.68 | N3: 36228.15 | O3: 9647.56 | P3: 0.2103 | Q3: 963.43 | R3: No
A4: 44927 | B4: 2023 | C4: Jan | D4: West | E4: Direct Sales | F4: Enterprise | G4: LAP-AIR-13 | H4: 79 | I4: 500.29 | J4: 0.04 | K4: 39523.19 | L4: 37942.26 | M4: 369.68 | N4: 29204.33 | O4: 8737.93 | P4: 0.2303 | Q4: 880.75 | R4: No
A5: 44927 | B5: 2023 | C5: Jan | D5: East | E5: Distributor | F5: SME | G5: LAP-AIR-13 | H5: 101 | I5: 485.51 | J5: 0.12 | K5: 49036.16 | L5: 43151.82 | M5: 369.68 | N5: 37337.18 | O5: 5814.65 | P5: 0.1347 | Q5: 582.19 | R5: No
A6: 44927 | B6: 2023 | C6: Jan | D6: North | E6: Retail | F6: Student | G6: LAP-PRO-15 | H6: 67 | I6: 696.1 | J6: 0.055 | K6: 46638.83 | L6: 44073.69 | M6: 548.55 | N6: 36752.85 | O6: 7320.84 | P6: 0.1661 | Q6: 877.95 | R6: No
A7: 44927 | B7: 2023 | C7: Jan | D7: South | E7: Direct Sales | F7: Enterprise | G7: LAP-PRO-15 | H7: 50 | I7: 703.1 | J7: 0.04 | K7: 35154.9 | L7: 33748.7 | M7: 548.55 | N7: 27427.5 | O7: 6321.2 | P7: 0.1873 | Q7: 837.82 | R7: No
A8: 44927 | B8: 2023 | C8: Jan | D8: West | E8: Distributor | F8: SME | G8: LAP-PRO-15 | H8: 103 | I8: 710.09 | J8: 0.12 | K8: 73139.68 | L8: 64362.92 | M8: 548.55 | N8: 56500.65 | O8: 7862.27 | P8: 0.1222 | Q8: 747.84 | R8: No
A9: 44927 | B9: 2023 | C9: Jan | D9: East | E9: Online | F9: Retail Customer | G9: LAP-PRO-15 | H9: 66 | I9: 689.11 | J9: 0.085 | K9: 45481 | L9: 41615.11 | M9: 548.55 | N9: 36204.3 | O9: 5410.81 | P9: 0.13 | Q9: 950.7 | R9: No
A10: 44927 | B10: 2023 | C10: Jan | D10: North | E10: Distributor | F10: SME | G10: TAB-LITE-10 | H10: 164 | I10: 221.49 | J10: 0.12 | K10: 36323.87 | L10: 31965 | M10: 151.05 | N10: 24772.2 | O10: 7192.8 | P10: 0.225 | Q10: 484.91 | R10: No
A11: 44927 | B11: 2023 | C11: Jan | D11: South | E11: Online | F11: Student | G11: TAB-LITE-10 | H11: 174 | I11: 223.71 | J11: 0.085 | K11: 38926.06 | L11: 35617.34 | M11: 151.05 | N11: 26282.7 | O11: 9334.64 | P11: 0.2621 | Q11: 785.82 | R11: No
A12: 44927 | B12: 2023 | C12: Jan | D12: West | E12: Retail | F12: Retail Customer | G12: TAB-LITE-10 | H12: 155 | I12: 225.94 | J12: 0.055 | K12: 35020.55 | L12: 33094.42 | M12: 151.05 | N12: 23412.75 | O12: 9681.67 | P12: 0.2925 | Q12: 730.4 | R12: No
A13: 44927 | B13: 2023 | C13: Jan | D13: East | E13: Distributor | F13: SME | G13: TAB-LITE-10 | H13: 130 | I13: 219.26 | J13: 0.12 | K13: 28503.93 | L13: 25083.46 | M13: 151.05 | N13: 19636.5 | O13: 5446.96 | P13: 0.2172 | Q13: 412.02 | R13: No
... A865: 45992 | B865: 2025 | C865: Dec | D865: East | E865: Retail | F865: Student | G865: WAR-EXT-2Y | H865: 208 | I865: 53.54 | J865: 0.065 | K865: 11137 | L865: 10413.09 | M865: 7.85 | N865: 1632.1 | O865: 8780.99 | P865: 0.8433 | Q865: 412.95 | R865: Yes

Sheet Master_Data
A1: SKU_ID | B1: Product_Name | C1: Product_Category | D1: Brand | E1: Launch_Date | F1: Lifecycle_Stage | G1: Base_Price | H1: Standard_Cost | I1: Target_Margin_% | J1: Base_Monthly_Demand | K1: Seasonality_Profile | L1: Strategic_Priority
A2: LAP-AIR-13 | B2: AeroBook 13 Laptop | C2: Laptop | D2: AeroTech | E2: 44652 | F2: Growth | G2: 492.9 | H2: 369.68 | I2: 0.25 | J2: 95 | K2: Student and festive demand | L2: High
A3: LAP-PRO-15 | B3: ProBook 15 Laptop | C3: Laptop | D3: ProEdge | E3: 44470 | F3: Mature | G3: 699.6 | H3: 548.55 | I3: 0.22 | J3: 70 | K3: Enterprise and year-end demand | L3: High
A4: TAB-LITE-10 | B4: LiteTab 10 Tablet | C4: Tablet | D4: TabNova | E4: 44774 | F4: Growth | G4: 222.6 | H4: 151.05 | I4: 0.32 | J4: 130 | K4: Student and online demand | L4: Medium
A5: ACC-MSE-WL | B5: Wireless Mouse | C5: Accessories | D5: ClickPro | E5: 43952 | F5: Mature | G5: 11.13 | H5: 5.57 | I5: 0.5 | J5: 520 | K5: High-volume add-on demand | L5: Medium
A6: SW-OFF-365 | B6: Office Software Bundle | C6: Software | D6: WorkSuite | E6: 44197 | F6: Growth | G6: 67.58 | H6: 14.31 | I6: 0.78 | J6: 160 | K6: SME and enterprise renewal demand | L6: High
A7: WAR-EXT-2Y | B7: Extended Warranty 2Y | C7: Warranty | D7: AssurePlus | E7: 43831 | F7: Mature | G7: 51.68 | H7: 7.16 | I7: 0.86 | J7: 145 | K7: Attached to laptop and tablet sales | L7: High

Sheet Assumed_scenario
A1: Scenario | B1: Unit Growth % | C1: Price Change % | D1: Cost Inflation % | E1: Discount Change % | F1: Marketing Spend Change %
A2: Base Case | B2: 0.08 | C2: 0.02 | D2: 0.04 | E2: 0 | F2: 0.05
A3: Optimistic | B3: 0.14 | C3: 0.04 | D3: 0.02 | E3: -0.01 | F3: 0.1
A4: Pessimistic | B4: 0.02 | C4: 0 | D4: 0.08 | E4: 0.02 | F4: -0.05
A5: Margin Recovery | B5: 0.05 | C5: 0.03 | D5: 0.01 | E5: -0.02 | F5: 0
A6: Growth Push | B6: 0.18 | C6: 0.01 | D6: 0.05 | E6: 0.03 | F6: 0.2
A8: Note: blue cells are editable scenario inputs. Change any value to flex the 2026 forecast.

Sheet company_profile
A1: forecasting
A2: The company has grown revenue strongly from 2023 to 2025, but gross margin percentage has declined from around 26.1% to 23.0%. Management wants a 2026 forecast and scenario model to decide whether to prioritise aggressive revenue growth, margin recovery, or balanced expansion. Participants must recommend one scenario to the board and explain trade-offs across revenue, margin, marketing spend, product mix, and channel performance.

Sheet Chart_Data
A1: Helper tables driving Dashboard charts (formula-linked, do not delete)
A3: 2025 Net Revenue by Channel | D3: 2025 Net Revenue by Product Category | G3: 2025 Actual margin vs target, by SKU
A4: Channel | B4: Net_Revenue | D4: Category | E4: Net_Revenue | G4: Product_Name | H4: Actual_GM_% | I4: Target_Margin_%
A5: Online | B5: =SUMIFS(Sales_Data!$L$2:$L$865,Sales_Data!$B$2:$B$865,2025,Sales_Data!$E$2:$E$865,$A5) -> 3992078.3 | D5: Laptop | E5: =SUMIFS(Sales_Data!$L$2:$L$865,Sales_Data!$B$2:$B$865,2025,Sales_Data!$G$2:$G$865,"LAP-AIR-13")+SUMIFS(Sales_Data!$L$2:$L$865,Sales_Data!$B$2:$B$865,2025,Sales_Data!$G$2:$G$865,"LAP-PRO-15") -> 7975974.1 | G5: =INDEX(Master_Data!$B$2:$B$7,MATCH("LAP-AIR-13",Master_Data!$A$2:$A$7,0)) -> AeroBook 13 Laptop | H5: =IFERROR(SUMIFS(Sales_Data!$O$2:$O$865,Sales_Data!$B$2:$B$865,2025,Sales_Data!$G$2:$G$865,"LAP-AIR-13")/SUMIFS(Sales_Data!$L$2:$L$865,Sales_Data!$B$2:$B$865,2025,Sales_Data!$G$2:$G$865,"LAP-AIR-13"),0) -> 0.13595481 | I5: =INDEX(Master_Data!$I$2:$I$7,MATCH("LAP-AIR-13",Master_Data!$A$2:$A$7,0)) -> 0.25
A6: Retail | B6: =SUMIFS(Sales_Data!$L$2:$L$865,Sales_Data!$B$2:$B$865,2025,Sales_Data!$E$2:$E$865,$A6) -> 3066349.9 | D6: Tablet | E6: =SUMIFS(Sales_Data!$L$2:$L$865,Sales_Data!$B$2:$B$865,2025,Sales_Data!$G$2:$G$865,"TAB-LITE-10") -> 2792436.4 | G6: =INDEX(Master_Data!$B$2:$B$7,MATCH("LAP-PRO-15",Master_Data!$A$2:$A$7,0)) -> ProBook 15 Laptop | H6: =IFERROR(SUMIFS(Sales_Data!$O$2:$O$865,Sales_Data!$B$2:$B$865,2025,Sales_Data!$G$2:$G$865,"LAP-PRO-15")/SUMIFS(Sales_Data!$L$2:$L$865,Sales_Data!$B$2:$B$865,2025,Sales_Data!$G$2:$G$865,"LAP-PRO-15"),0) -> 0.097244494 | I6: =INDEX(Master_Data!$I$2:$I$7,MATCH("LAP-PRO-15",Master_Data!$A$2:$A$7,0)) -> 0.22
A7: Direct Sales | B7: =SUMIFS(Sales_Data!$L$2:$L$865,Sales_Data!$B$2:$B$865,2025,Sales_Data!$E$2:$E$865,$A7) -> 1717358.4 | D7: Software | E7: =SUMIFS(Sales_Data!$L$2:$L$865,Sales_Data!$B$2:$B$865,2025,Sales_Data!$G$2:$G$865,"SW-OFF-365") -> 979571.14 | G7: =INDEX(Master_Data!$B$2:$B$7,MATCH("TAB-LITE-10",Master_Data!$A$2:$A$7,0)) -> LiteTab 10 Tablet | H7: =IFERROR(SUMIFS(Sales_Data!$O$2:$O$865,Sales_Data!$B$2:$B$865,2025,Sales_Data!$G$2:$G$865,"TAB-LITE-10")/SUMIFS(Sales_Data!$L$2:$L$865,Sales_Data!$B$2:$B$865,2025,Sales_Data!$G$2:$G$865,"TAB-LITE-10"),0) -> 0.2107843 | I7: =INDEX(Master_Data!$I$2:$I$7,MATCH("TAB-LITE-10",Master_Data!$A$2:$A$7,0)) -> 0.32
A8: Distributor | B8: =SUMIFS(Sales_Data!$L$2:$L$865,Sales_Data!$B$2:$B$865,2025,Sales_Data!$E$2:$E$865,$A8) -> 4020646.7 | D8: Accessories | E8: =SUMIFS(Sales_Data!$L$2:$L$865,Sales_Data!$B$2:$B$865,2025,Sales_Data!$G$2:$G$865,"ACC-MSE-WL") -> 499870.79 | G8: =INDEX(Master_Data!$B$2:$B$7,MATCH("ACC-MSE-WL",Master_Data!$A$2:$A$7,0)) -> Wireless Mouse | H8: =IFERROR(SUMIFS(Sales_Data!$O$2:$O$865,Sales_Data!$B$2:$B$865,2025,Sales_Data!$G$2:$G$865,"ACC-MSE-WL")/SUMIFS(Sales_Data!$L$2:$L$865,Sales_Data!$B$2:$B$865,2025,Sales_Data!$G$2:$G$865,"ACC-MSE-WL"),0) -> 0.41868206 | I8: =INDEX(Master_Data!$I$2:$I$7,MATCH("ACC-MSE-WL",Master_Data!$A$2:$A$7,0)) -> 0.5
D9: Warranty | E9: =SUMIFS(Sales_Data!$L$2:$L$865,Sales_Data!$B$2:$B$865,2025,Sales_Data!$G$2:$G$865,"WAR-EXT-2Y") -> 548580.81 | G9: =INDEX(Master_Data!$B$2:$B$7,MATCH("SW-OFF-365",Master_Data!$A$2:$A$7,0)) -> Office Software Bundle | H9: =IFERROR(SUMIFS(Sales_Data!$O$2:$O$865,Sales_Data!$B$2:$B$865,2025,Sales_Data!$G$2:$G$865,"SW-OFF-365")/SUMIFS(Sales_Data!$L$2:$L$865,Sales_Data!$B$2:$B$865,2025,Sales_Data!$G$2:$G$865,"SW-OFF-365"),0) -> 0.75788647 | I9: =INDEX(Master_Data!$I$2:$I$7,MATCH("SW-OFF-365",Master_Data!$A$2:$A$7,0)) -> 0.78
G10: =INDEX(Master_Data!$B$2:$B$7,MATCH("WAR-EXT-2Y",Master_Data!$A$2:$A$7,0)) -> Extended Warranty 2Y | H10: =IFERROR(SUMIFS(Sales_Data!$O$2:$O$865,Sales_Data!$B$2:$B$865,2025,Sales_Data!$G$2:$G$865,"WAR-EXT-2Y")/SUMIFS(Sales_Data!$L$2:$L$865,Sales_Data!$B$2:$B$865,2025,Sales_Data!$G$2:$G$865,"WAR-EXT-2Y"),0) -> 0.84613685 | I10: =INDEX(Master_Data!$I$2:$I$7,MATCH("WAR-EXT-2Y",Master_Data!$A$2:$A$7,0)) -> 0.86
A12: 2026 Scenario comparison (for chart)
A13: Scenario | B13: Net_Revenue_2026 | C13: Gross_Margin_%_2026
A14: =Forecast_2026!A37 -> Base Case | B14: =Forecast_2026!D37 -> 14096551 | C14: =Forecast_2026!G37 -> 0.21476611
A15: =Forecast_2026!A38 -> Optimistic | B15: =Forecast_2026!D38 -> 15339366 | C15: =Forecast_2026!G38 -> 0.2529453
A16: =Forecast_2026!A39 -> Pessimistic | B16: =Forecast_2026!D39 -> 12763439 | C16: =Forecast_2026!G39 -> 0.14942812
A17: =Forecast_2026!A40 -> Margin Recovery | B17: =Forecast_2026!D40 -> 14145686 | C17: =Forecast_2026!G40 -> 0.2611752
A18: =Forecast_2026!A41 -> Growth Push | B18: =Forecast_2026!D41 -> 14744409 | C18: =Forecast_2026!G41 -> 0.1718696
